kbbqgraph/KBBQGraph.c
kbbqgraph/__init__.py
kbbqgraph/kbbqdll.dll
kbbqgraph/kbbqdll.so
kbbqgraph-0.1.0.dist-info/licenses/LICENSE
kbbqgraph-0.1.0.dist-info/METADATA
kbbqgraph-0.1.0.dist-info/WHEEL
kbbqgraph-0.1.0.dist-info/top_level.txt
kbbqgraph-0.1.0.dist-info/RECORD
