Metadata-Version: 2.4
Name: kbbqgraph
Version: 0.1.0
Summary: Fast low-level graph utilities for metabolomics pipelines (BBQGraph)
Author-email: Daniel Hitchcock <daniel.s.hitchcock@gmail.com>
License: MIT License
Project-URL: Repository, https://github.com/broadinstitute/kbbqgraph
Keywords: graph,metabolomics,ctypes,bbqgraph
Classifier: Programming Language :: Python :: 3
Classifier: Programming Language :: C
Classifier: Programming Language :: Python :: Implementation :: CPython
Classifier: Operating System :: OS Independent
Classifier: License :: OSI Approved :: MIT License
Requires-Python: >=3.8
License-File: LICENSE
Requires-Dist: numpy
Dynamic: license-file
